finpie/__init__.py
finpie/base.py
finpie/fundamental_data/__init__.py
finpie/fundamental_data/finviz.py
finpie/fundamental_data/fool.py
finpie/fundamental_data/fundamentals.py
finpie/fundamental_data/macrotrends.py
finpie/fundamental_data/mwatch.py
finpie/fundamental_data/yahoo.py
finpie/news_data/__init__.py
finpie/news_data/clean_news.py
finpie/news_data/cnbc_news.py
finpie/news_data/ft_news.py
finpie/news_data/news.py
finpie/news_data/wsj_news.py
finpie/other_data/__init__.py
finpie/other_data/cftc.py
finpie/other_data/stock_symbols.py
finpie/price_data/__init__.py
finpie/price_data/price_data.py
finpie-0.1400.dist-info/LICENSE
finpie-0.1400.dist-info/METADATA
finpie-0.1400.dist-info/WHEEL
finpie-0.1400.dist-info/top_level.txt
finpie-0.1400.dist-info/zip-safe
finpie-0.1400.dist-info/RECORD
