Metadata-Version: 2.1
Name: finpie
Version: 0.1400
Summary: Simple library to download some financial data
Home-page: https://github.com/peterlacour/finpie
Author: Peter la Cour
Author-email: pe.lacour@gmail.com
License: MIT
Keywords: yahoo finance,news data,company fundamentals,economic data,eia data,stock prices,option prices
License-File: LICENSE
Requires-Dist: pandas (>=1.0.1)
Requires-Dist: selenium (>=3.14.0)
Requires-Dist: numpy (>=1.18.2)
Requires-Dist: tqdm
Requires-Dist: beautifulsoup4
Requires-Dist: html5lib
Requires-Dist: xlrd
Requires-Dist: requests-html
Requires-Dist: requests
Requires-Dist: webdriver-manager
Requires-Dist: dateparser
